__init__.py
common/__init__.py
common/constants/__init__.py
common/constants/common_constants.py
common/constants/logging_constants.py
common/exceptions/__init__.py
common/exceptions/main_exceptions.py
common/io_operations/__init__.py
common/io_operations/image_downloader.py
common/io_operations/io_operations.py
common/io_operations/request_factory.py
common/logging/__init__.py
common/logging/logging_setup.py
common/logging/loguru_setup.py
common/logging/utils/__init__.py
common/logging/utils/color_formatter.py
common/logging/utils/log_rotator.py
common/logging/utils/logging_wrappers.py
common/logging/utils/loguru_wrappers.py
common/logging/utils/padding_formatter.py
common/utils/__init__.py
common/utils/string_builder.py
common/validations/__init__.py
common/validations/parameter_validations.py
common/validations/reddit_api_validations.py
common/validations/url_validations.py
core/__init__.py
core/main.py
core/api/__init__.py
core/api/reddit_api.py
core/helper/__init__.py
core/helper/main_helper.py
core/scraper/__init__.py
core/scraper/comment_scraper.py
core/scraper/scraper_helper.py
core/scraper/thread_scraper.py
redscrap-0.0.4.dist-info/LICENSE
redscrap-0.0.4.dist-info/METADATA
redscrap-0.0.4.dist-info/WHEEL
redscrap-0.0.4.dist-info/entry_points.txt
redscrap-0.0.4.dist-info/top_level.txt
redscrap-0.0.4.dist-info/RECORD
